[
  {
    "word": "deference",
    "definition": "respectful submission or yielding to the judgment of another",
    "sentence": "In deference to her experience, they accepted her recommendations."
  },
  {
    "word": "empathy",
    "definition": "the ability to understand and share the feelings of another",
    "sentence": "Her empathy towards the victims of the disaster was palpable."
  },
  {
    "word": "frivolous",
    "definition": "not having any serious purpose or value",
    "sentence": "He was criticized for spending money on frivolous items."
  },
  {
    "word": "incessant",
    "definition": "continuing without pause or interruption",
    "sentence": "The incessant noise from the construction site was unbearable."
  },
  {
    "word": "kerfuffle",
    "definition": "a commotion or fuss, especially one caused by conflicting views",
    "sentence": "There was a kerfuffle over the seating arrangements at the event."
  },
  {
    "word": "lucrative",
    "definition": "producing a great deal of profit",
    "sentence": "She found a lucrative job in the tech industry."
  },
  {
    "word": "oblivious",
    "definition": "not aware of or concerned about what is happening",
    "sentence": "She was oblivious to the chaos around her."
  },
  {
    "word": "plausible",
    "definition": "seeming reasonable or probable",
    "sentence": "He gave a plausible explanation for his absence."
  },
  {
    "word": "superfluous",
    "definition": "unnecessary, especially through being more than enough",
    "sentence": "The report was filled with superfluous details that confused the issue."
  },
  {
    "word": "tenacious",
    "definition": "tending to keep a firm hold of something",
    "sentence": "Her tenacious spirit helped her overcome many obstacles."
  }
]